{
  "timestamp": "2025-01-31T16:43:16.391343",
  "context": {
    "input_shape": [
      3,
      3
    ],
    "output_shape": [
      3,
      3
    ],
    "input_values": [
      0,
      1
    ],
    "output_values": [
      0,
      1
    ],
    "num_examples": 2,
    "insights": [],
    "patterns": [],
    "complexity_estimate": 0.5
  },
  "patterns": [
    {
      "pattern": "Both strategies are constructed using a minimalist approach that leverages a single, clearly defined primitive operation (inversion) applied uniformly across the grid.",
      "confidence": 1.0
    },
    {
      "pattern": "The strategies' creation involves mapping each cell's binary value to its opposite, which indicates a preference for simple, element-wise transformations in grid-based ARC tasks.",
      "confidence": 0.95
    }
  ],
  "success": true,
  "input_size": 3
}